setup.py
should/__init__.py
should/should.py
should.egg-info/PKG-INFO
should.egg-info/SOURCES.txt
should.egg-info/dependency_links.txt
should.egg-info/entry_points.txt
should.egg-info/not-zip-safe
should.egg-info/top_level.txt
should/ext/__init__.py
should/ext/chains.py
should/ext/containers.py
should/ext/errors.py
should/ext/numbers.py
should/ext/properties.py
should/ext/strings.py
should/ext/types.py
should/ext/values.py