Metadata-Version: 1.0
Name: should
Version: 0.5.4
Summary: assert with should
Home-page: https://github.com/Ralph-Wang/should
Author: Ralph-Wang
Author-email: ralph.wang1024@gmail.com
License: MIT
Keywords: assert,should,test,BDD
Platform: UNKNOWN
